{
 "polysig": {
      "miniDapp": "polysig.minidapp",
      "icon": "polysig/assets/polysig.png",
      "conf": "polysig/minidapp.conf"
  },
  "block": {
      "miniDapp": "block.minidapp",
      "icon": "block/assets/block.png",
      "conf": "block/minidapp.conf"
  },
    "wallet": {
      "miniDapp": "wallet.minidapp",
      "icon": "wallet/assets/wallet.png",
      "conf": "wallet/minidapp.conf"
  },
    "coinmaster": {
      "miniDapp": "coinmaster.minidapp",
      "icon": "coinmaster/assets/coin.png",
      "conf": "coinmaster/minidapp.conf"
  },
  "futurecash": {
    "miniDapp": "futurecash.minidapp",
    "icon": "futurecash/futurecash.png",
    "conf": "futurecash/minidapp.conf"
  } 
}
